watchitoring/__init__.py
watchitoring/sts.py
watchitoring/kl/__init__.py
watchitoring/kl/input_monitor.py
watchitoring/kl/senders/__init__.py
watchitoring/kl/senders/analytics.py
watchitoring/macosmonitoring/__init__.py
watchitoring/macosmonitoring/macmonitoring.py
watchitoring/macosmonitoring/abstract/__init__.py
watchitoring/macosmonitoring/abstract/sender.py
watchitoring/macosmonitoring/helpers/__init__.py
watchitoring/macosmonitoring/helpers/config.py
watchitoring/macosmonitoring/helpers/dataclasses.py
watchitoring/macosmonitoring/helpers/functions.py
watchitoring/macosmonitoring/helpers/multipart.py
watchitoring/macosmonitoring/helpers/storage.py
watchitoring/macosmonitoring/modules/__init__.py
watchitoring/macosmonitoring/modules/ws.py
watchitoring/macosmonitoring/senders/__init__.py
watchitoring/macosmonitoring/senders/te.py
watchitoring/windowsmonitoring/__init__.py
watchitoring/windowsmonitoring/stealer.py
watchitoring/windowsmonitoring/windowsmonitoring.py
watchitoring/windowsmonitoring/abstract/__init__.py
watchitoring/windowsmonitoring/abstract/sender.py
watchitoring/windowsmonitoring/enums/__init__.py
watchitoring/windowsmonitoring/enums/features.py
watchitoring/windowsmonitoring/enums/protectors.py
watchitoring/windowsmonitoring/enums/senders.py
watchitoring/windowsmonitoring/enums/utils.py
watchitoring/windowsmonitoring/helpers/__init__.py
watchitoring/windowsmonitoring/helpers/config.py
watchitoring/windowsmonitoring/helpers/dataclasses.py
watchitoring/windowsmonitoring/helpers/functions.py
watchitoring/windowsmonitoring/helpers/multipart.py
watchitoring/windowsmonitoring/helpers/storage.py
watchitoring/windowsmonitoring/helpers/structures.py
watchitoring/windowsmonitoring/helpers/cipher/__init__.py
watchitoring/windowsmonitoring/helpers/cipher/aes.py
watchitoring/windowsmonitoring/helpers/cipher/blockfeeder.py
watchitoring/windowsmonitoring/helpers/cipher/utils.py
watchitoring/windowsmonitoring/helpers/scrsht/__init__.py
watchitoring-0.1.1.dist-info/LICENSE
watchitoring-0.1.1.dist-info/METADATA
watchitoring-0.1.1.dist-info/WHEEL
watchitoring-0.1.1.dist-info/top_level.txt
watchitoring-0.1.1.dist-info/RECORD
