Metadata-Version: 2.2
Name: watchitoring
Version: 0.1.1
Summary: Кроссплатформенная библиотека для мониторинга системных событий
Home-page: https://github.com/DGaliaf/watchitoring
Author: AtlasKunner
Classifier: Programming Language :: Python :: 3
Classifier: License :: OSI Approved :: MIT License
Classifier: Operating System :: OS Independent
Classifier: Development Status :: 3 - Alpha
Requires-Python: >=3.6
License-File: LICENSE
Requires-Dist: pynput>=1.7.6
Provides-Extra: windows
Requires-Dist: pywin32>=306; extra == "windows"
Provides-Extra: macos
Requires-Dist: pyobjc-framework-Cocoa>=9.2; extra == "macos"
Dynamic: author
Dynamic: classifier
Dynamic: description
Dynamic: description-content-type
Dynamic: home-page
Dynamic: provides-extra
Dynamic: requires-dist
Dynamic: requires-python
Dynamic: summary
